ldm/__init__.py
ldm/util.py
ldm/data/__init__.py
ldm/data/util.py
ldm/models/__init__.py
ldm/models/autoencoder.py
ldm/models/diffusion/__init__.py
ldm/models/diffusion/ddim.py
ldm/models/diffusion/ddpm.py
ldm/models/diffusion/plms.py
ldm/models/diffusion/sampling_util.py
ldm/models/diffusion/dpm_solver/__init__.py
ldm/models/diffusion/dpm_solver/dpm_solver.py
ldm/models/diffusion/dpm_solver/sampler.py
ldm/modules/__init__.py
ldm/modules/attention.py
ldm/modules/ema.py
ldm/modules/diffusionmodules/__init__.py
ldm/modules/diffusionmodules/model.py
ldm/modules/diffusionmodules/openaimodel.py
ldm/modules/diffusionmodules/upscaling.py
ldm/modules/diffusionmodules/util.py
ldm/modules/distributions/__init__.py
ldm/modules/distributions/distributions.py
ldm/modules/encoders/__init__.py
ldm/modules/encoders/modules.py
ldm/modules/image_degradation/__init__.py
ldm/modules/image_degradation/bsrgan.py
ldm/modules/image_degradation/bsrgan_light.py
ldm/modules/image_degradation/utils_image.py
ldm/modules/midas/__init__.py
ldm/modules/midas/api.py
ldm/modules/midas/utils.py
ldm/modules/midas/midas/__init__.py
ldm/modules/midas/midas/base_model.py
ldm/modules/midas/midas/blocks.py
ldm/modules/midas/midas/dpt_depth.py
ldm/modules/midas/midas/midas_net.py
ldm/modules/midas/midas/midas_net_custom.py
ldm/modules/midas/midas/transforms.py
ldm/modules/midas/midas/vit.py
stable_diffusion_sdkit-2.1.5.dist-info/LICENSE
stable_diffusion_sdkit-2.1.5.dist-info/LICENSE-MODEL
stable_diffusion_sdkit-2.1.5.dist-info/METADATA
stable_diffusion_sdkit-2.1.5.dist-info/WHEEL
stable_diffusion_sdkit-2.1.5.dist-info/top_level.txt
stable_diffusion_sdkit-2.1.5.dist-info/RECORD
