Metadata-Version: 2.1
Name: stable-diffusion-sdkit
Version: 2.1.5
Summary: High-Resolution Image Synthesis with Latent Diffusion Models. This is a wrapper around the original repo, to allow installing via pip.
Project-URL: Homepage, https://github.com/Stability-AI/stablediffusion
Project-URL: Bug Tracker, https://github.com/Stability-AI/stablediffusion/issues
Classifier: Programming Language :: Python :: 3
Classifier: License :: OSI Approved :: MIT License
Classifier: Operating System :: OS Independent
Requires-Python: >=3.8
License-File: LICENSE
License-File: LICENSE-MODEL
Requires-Dist: albumentations ==1.3.0
Requires-Dist: opencv-python ==4.6.0.66
Requires-Dist: pytorch-lightning ==1.4.2
Requires-Dist: omegaconf ==2.1.1
Requires-Dist: test-tube >=0.7.5
Requires-Dist: einops ==0.3.0
Requires-Dist: transformers ==4.33.2
Requires-Dist: kornia ==0.6
Requires-Dist: open-clip-torch ==2.0.2
Requires-Dist: torchmetrics ==0.6.0
Requires-Dist: tqdm
Requires-Dist: huggingface-hub >=0.10.0
